LICENSE
MANIFEST.in
README.md
requirements.pip
setup.py
tx_logging/__init__.py
tx_logging/observers.py
tx_logging.egg-info/PKG-INFO
tx_logging.egg-info/SOURCES.txt
tx_logging.egg-info/dependency_links.txt
tx_logging.egg-info/requires.txt
tx_logging.egg-info/top_level.txt
tx_logging/tests/__init__.py
tx_logging/tests/observers.py
tx_logging/tests/test_logging.py
tx_logging/tests/test_observers.py