Metadata-Version: 1.1
Name: tx-logging
Version: 1.0.0
Summary: Extends Twisted log facilities.
Home-page: https://github.com/oblalex/tx-logging
Author: Alexander Oblovatniy
Author-email: oblovatniy@gmail.com
License: GPL v2
Platform: UNKNOWN
Classifier: Development Status :: 5 - Production/Stable
Classifier: Intended Audience :: Developers
Classifier: License :: Free for non-commercial use
Classifier: License :: OSI Approved :: GNU General Public License v2 (GPLv2)
Classifier: Natural Language :: English
Classifier: Operating System :: OS Independent
Classifier: Programming Language :: Python :: 2.7
Classifier: Topic :: Software Development :: Libraries
Classifier: Framework :: Twisted
